MCML/__init__.py
MCML/modules.py
MCML/tools.py
MCML-0.0.1.dist-info/LICENSE
MCML-0.0.1.dist-info/METADATA
MCML-0.0.1.dist-info/WHEEL
MCML-0.0.1.dist-info/top_level.txt
MCML-0.0.1.dist-info/RECORD
