Metadata-Version: 2.1
Name: MCML
Version: 0.0.1
Summary: Semi-supervised Dimensionality Reduction for Multi-Class, Multi-Label Data
Home-page: https://github.com/pachterlab/MCML
Author: Tara Chari
Author-email: tarachari3@gmail.com
License: UNKNOWN
Project-URL: Bug Tracker, https://github.com/pachterlab/MCML/issues
Platform: UNKNOWN
Classifier: Programming Language :: Python :: 3
Classifier: License :: OSI Approved :: BSD License
Classifier: Operating System :: OS Independent
Requires-Python: >=3.7
License-File: LICENSE
Requires-Dist: setuptools (>=49)
Requires-Dist: wheel
Requires-Dist: torch (>=1.9.0)
Requires-Dist: numpy (>=1.21.0)
Requires-Dist: pandas (>=1.2.5)
Requires-Dist: matplotlib (>=3.4.2)
Requires-Dist: torchsummary (>=1.5.1)
Requires-Dist: scikit-learn (>=0.24.2)
